libravatar/__init__.py
libravatar/_dns.py
libravatar/_query.py
libravatar_py-1.0.1.dist-info/LICENSE
libravatar_py-1.0.1.dist-info/METADATA
libravatar_py-1.0.1.dist-info/WHEEL
libravatar_py-1.0.1.dist-info/RECORD
