Metadata-Version: 2.1
Name: libravatar-py
Version: 1.0.1
Summary: Friendly fork of pyLibravatar for async support.
License: MIT
Author: baseplate-admin
Requires-Python: >=3.8,<4.0
Classifier: License :: OSI Approved :: MIT License
Classifier: Programming Language :: Python :: 3
Classifier: Programming Language :: Python :: 3.8
Classifier: Programming Language :: Python :: 3.9
Classifier: Programming Language :: Python :: 3.10
Classifier: Programming Language :: Python :: 3.11
Requires-Dist: dnspython (>=2.4.2,<3.0.0)
Requires-Dist: httpx (>=0.25.0,<0.26.0)
